drop_columns_by_treshold/__init__.py
drop_columns_by_treshold/drop_columns_by_treshold.py
drop_columns_by_treshold-0.0.8.dist-info/LICENSE
drop_columns_by_treshold-0.0.8.dist-info/METADATA
drop_columns_by_treshold-0.0.8.dist-info/WHEEL
drop_columns_by_treshold-0.0.8.dist-info/top_level.txt
drop_columns_by_treshold-0.0.8.dist-info/RECORD
