Metadata-Version: 2.1
Name: drop_columns_by_treshold
Version: 0.0.8
Summary: drop_columns_by_treshold
Home-page: https://github.com/ganbaaelmer/drop_columns_by_treshold.git
Author: Ganbaatar Bold
Author-email: elmerganbaa <elmerganbaa@gmail.com>
Project-URL: Homepage, https://github.com/ganbaaelmer/drop_columns_by_treshold
Project-URL: Issues, https://github.com/ganbaaelmer/drop_columns_by_treshold
Classifier: Programming Language :: Python :: 3
Classifier: License :: OSI Approved :: MIT License
Classifier: Operating System :: OS Independent
Requires-Python: >=3.6
License-File: LICENSE
